{"title":"Update for Windows 10 Version 1809 - KB4023057 (17763.2021)","ring":"RETAIL","flight":"Active","arch":"amd64","build":"17763.2021","checkBuild":"10.0.17763.1","sku":72,"containsCU":1,"created":1622581721,"files":{"532cadb26dde2693e476f5abeedb25df59e7aa86":{"name":"compdb.xml.cab","size":"9071"},"6ae5a252bdf73bb7aa791a46fe07401e9fef681a":{"name":"unifiedinstaller.exe","size":"131384"},"a183c32697155cc09c9bbc5a6a8b2d12e65fc4c7":{"name":"UpdHealthTools.cab","size":"1102422"},"dbe317c6e4187f0bb39fa966b53d66d30ab7ccfe":{"name":"ExeUpdateAgentDeployment.cab","size":"1803425"}}}
